dmoop/__init__.py
dynamic_moops-0.0.1.dev0.dist-info/METADATA
dynamic_moops-0.0.1.dev0.dist-info/WHEEL
dynamic_moops-0.0.1.dev0.dist-info/top_level.txt
dynamic_moops-0.0.1.dev0.dist-info/RECORD
